README.md
setup.py
paper/__init__.py
paper/cli.py
paper/hypergraph_binning_main/__init__.py
paper/hypergraph_binning_main/functions.py
paper_lib_collective.egg-info/PKG-INFO
paper_lib_collective.egg-info/SOURCES.txt
paper_lib_collective.egg-info/dependency_links.txt
paper_lib_collective.egg-info/entry_points.txt
paper_lib_collective.egg-info/top_level.txt
tests/__init__.py